jungle/__init__.py
junglelin-0.2.dist-info/METADATA
junglelin-0.2.dist-info/WHEEL
junglelin-0.2.dist-info/top_level.txt
junglelin-0.2.dist-info/RECORD
