Metadata-Version: 2.1
Name: junglelin
Version: 0.2
Summary: The funniest joke in the world by kunlin
Home-page: UNKNOWN
Author: kunlin
Author-email: tanlandy6@gmail.com
License: MIT
Platform: UNKNOWN
